mlky/__init__.py
mlky/cli/__init__.py
mlky/cli/cli.py
mlky/configs/__init__.py
mlky/configs/base.py
mlky/configs/builtins.py
mlky/configs/dict.py
mlky/configs/funcs.py
mlky/configs/interpolate.py
mlky/configs/list.py
mlky/configs/null.py
mlky/configs/sect.py
mlky/configs/types.py
mlky/configs/var.py
mlky/utils/__init__.py
mlky/utils/formatters.py
mlky/utils/funcs.py
mlky/utils/io.py
mlky/utils/prettyslice.py
mlky/utils/templates.py
mlky/utils/track.py
mlky-2024.6.1.dist-info/LICENSE
mlky-2024.6.1.dist-info/METADATA
mlky-2024.6.1.dist-info/WHEEL
mlky-2024.6.1.dist-info/entry_points.txt
mlky-2024.6.1.dist-info/top_level.txt
mlky-2024.6.1.dist-info/RECORD
