Metadata-Version: 2.1
Name: mlky
Version: 2024.6.1
Summary: Machine Learning key utilities
Author: James Montgomery
Author-email: J.Montgomery@jpl.nasa.gov
Classifier: Programming Language :: Python :: 3
Classifier: License :: OSI Approved :: MIT License
Classifier: Operating System :: OS Independent
License-File: LICENSE
Requires-Dist: click
Requires-Dist: PyYAML
Provides-Extra: dev
Requires-Dist: build ; extra == 'dev'
